issx/__init__.py
issx/cli.py
issx/cli_utils.py
issx/clients/__init__.py
issx/clients/exceptions.py
issx/clients/gitlab.py
issx/clients/interfaces.py
issx/clients/redmine.py
issx/domain/__init__.py
issx/domain/config.py
issx/domain/issues.py
issx/instance_managers/__init__.py
issx/instance_managers/config_parser.py
issx/instance_managers/managers.py
issx/py.typed
issx/services.py
issx-0.6.0.dist-info/LICENCE
issx-0.6.0.dist-info/METADATA
issx-0.6.0.dist-info/WHEEL
issx-0.6.0.dist-info/entry_points.txt
issx-0.6.0.dist-info/RECORD
