Metadata-Version: 2.1
Name: issx
Version: 0.6.0
Summary: Tool for synchronizing issues between different services
Home-page: https://nekeal.github.io/issx
License: MIT
Author: nekeal
Author-email: szymon.sc.cader@gmail.com
Requires-Python: >=3.11,<4.0
Classifier: Development Status :: 4 - Beta
Classifier: Intended Audience :: Developers
Classifier: License :: OSI Approved :: MIT License
Classifier: Operating System :: OS Independent
Classifier: Programming Language :: Python
Classifier: Programming Language :: Python :: 3
Classifier: Programming Language :: Python :: 3.11
Classifier: Programming Language :: Python :: 3.12
Classifier: Topic :: Software Development :: Libraries :: Python Modules
Classifier: Typing :: Typed
Requires-Dist: attrs (>=23.2.0,<24.0.0)
Requires-Dist: python-gitlab (>=4.4.0,<5.0.0)
Requires-Dist: python-redmine (>=2.5.0,<3.0.0)
Requires-Dist: typer (>=0.12.0,<0.13.0)
Project-URL: Documentation, https://nekeal.github.io/issx
Project-URL: Repository, https://github.com/nekeal/issx
